[
  {
    "title": "RL-MACRO: A Cybernetic Closed-Loop Intelligence Framework for Multimodal Adaptive Robotic Craniotomy",
    "author": "Xiao Zhang et al.",
    "year": "2026",
    "url": "http://arxiv.org/abs/2607.21113v1"
  },
  {
    "title": "EdgeFaaS: A Function-based Framework for Edge Computing",
    "author": "Neha Vadnere et al.",
    "year": "2026",
    "url": "http://arxiv.org/abs/2607.14489v1"
  },
  {
    "title": "SynapticOS: An Inference-First Runtime Architecture for Neural Processing Units on Resource-Constrained Microcontrollers",
    "author": "Dimitrios Kafetzis",
    "year": "2026",
    "url": "http://arxiv.org/abs/2607.12606v1"
  },
  {
    "title": "Internet of Agentic Things: Networked AI Agents for Closed-Loop IoT Orchestration",
    "author": "Quanyan Zhu",
    "year": "2026",
    "url": "http://arxiv.org/abs/2607.12662v1"
  },
  {
    "title": "RT-SHCUA: Real-Time Self-Hosted Computer-Use Agent for UAV Control",
    "author": "Di Lu et al.",
    "year": "2026",
    "url": "http://arxiv.org/abs/2607.17951v1"
  },
  {
    "title": "Interaction Dynamics Modeling and Predictive Control for Safe Steerable Catheter--Tissue Interaction",
    "author": "Yongyan Cao",
    "year": "2026",
    "url": "http://arxiv.org/abs/2607.20939v1"
  },
  {
    "title": "Factorized Spatio-Temporal Convolutions for Human Pose Estimation from Planar Lidar",
    "author": "Simone Arreghini et al.",
    "year": "2026",
    "url": "http://arxiv.org/abs/2607.21309v1"
  },
  {
    "title": "ESBMC-Arduino: Closing the Deployment Gap for Formal Verification of Open-Hardware PLCs",
    "author": "Pierre Dantas et al.",
    "year": "2026",
    "url": "http://arxiv.org/abs/2607.08550v1"
  },
  {
    "title": "Barzilai-Borwein Fails Superlinear Convergence on an Open Set of Quadratics for Every Dimension $n\\geq 4$",
    "author": "Dawei Li et al.",
    "year": "2026",
    "url": "http://arxiv.org/abs/2607.21579v1"
  },
  {
    "title": "Synthetic data generation framework for quality control automation in gravure printing",
    "author": "Korota Arsène Coulibaly et al.",
    "year": "2026",
    "url": "http://arxiv.org/abs/2607.21577v1"
  }
]