[
  {
    "title": "EdgeFaaS: A Function-based Framework for Edge Computing",
    "author": "Neha Vadnere et al.",
    "year": "2026",
    "url": "http://arxiv.org/abs/2607.14489v1"
  },
  {
    "title": "Cluster-Aware Matching via Laplacian Optimal Transport",
    "author": "Gabriel Samberg et al.",
    "year": "2026",
    "url": "http://arxiv.org/abs/2607.16178v1"
  },
  {
    "title": "F-ACVAE: A Federated Adaptive Conditional Variational Auto-Encoder for Privacy-Preserving Intrusion Detection in IoT Networks",
    "author": "Mohammad Ansarimehr et al.",
    "year": "2026",
    "url": "http://arxiv.org/abs/2607.04698v1"
  },
  {
    "title": "Physics-enhanced reinforcement learning for real-time optimal control of dynamical systems",
    "author": "Matteo Tomasetto et al.",
    "year": "2026",
    "url": "http://arxiv.org/abs/2607.16177v1"
  },
  {
    "title": "PRISA: Proactive Infrastructure LiDAR Framework for Intersection Safety Assessment",
    "author": "Tam Bang et al.",
    "year": "2026",
    "url": "http://arxiv.org/abs/2607.16156v1"
  },
  {
    "title": "Internet of Agentic Things: Networked AI Agents for Closed-Loop IoT Orchestration",
    "author": "Quanyan Zhu",
    "year": "2026",
    "url": "http://arxiv.org/abs/2607.12662v1"
  },
  {
    "title": "Compound Interference Recognition for LR-FHSS Satellite IoT Uplinks via Multi-Domain Instance Fusion",
    "author": "H. Xu et al.",
    "year": "2026",
    "url": "http://arxiv.org/abs/2607.11488v1"
  },
  {
    "title": "When Do Multi-Agent Systems Help? An Information Bottleneck Perspective",
    "author": "Wendi Yu et al.",
    "year": "2026",
    "url": "http://arxiv.org/abs/2607.16133v1"
  },
  {
    "title": "A Blueprint for Equilibrium-Based Differentiable Continuous-Variable Thermodynamic Computing",
    "author": "Owen Lockwood et al.",
    "year": "2026",
    "url": "http://arxiv.org/abs/2607.16183v1"
  },
  {
    "title": "Behaviour-Conditioned Neural Processes for Adaptive Residential Short-Term Load Forecasting",
    "author": "Ramin Soleimani et al.",
    "year": "2026",
    "url": "http://arxiv.org/abs/2607.16168v1"
  }
]